Belkhair/__init__.py
Belkhair/date_utils.py
Belkhair/math_utils.py
Belkhair/string_utils.py
Belkhair-0.1.0.dist-info/METADATA
Belkhair-0.1.0.dist-info/WHEEL
Belkhair-0.1.0.dist-info/top_level.txt
Belkhair-0.1.0.dist-info/RECORD
