Metadata-Version: 2.1
Name: Belkhair
Version: 0.1.0
Summary: A utility package for math, string, and date operations
Author: Ali Belkhair
License: MIT
Classifier: Programming Language :: Python :: 3
Classifier: License :: OSI Approved :: MIT License
Classifier: Operating System :: OS Independent
Requires-Python: >=3.6
